{
  "analysis": {
    "totalFiles": 39,
    "categorizedFiles": {
      "controller": 6,
      "service": 0,
      "dao": 7,
      "other": 26
    },
    "analysisDate": "2025-07-25T12:44:15.950Z"
  },
  "classes": [
    {
      "filePath": "/home/runner/workspace/java-codebase/src/main/java/com/sparta/engineering72/sakilaproject/SakilaProjectApplication.java",
      "category": "other",
      "className": "SakilaProjectApplication",
      "description": "Other Java class",
      "methods": [],
      "complexityLevel": "low",
      "internalDependencies": [],
      "annotations": []
    },
    {
      "filePath": "/home/runner/workspace/java-codebase/src/main/java/com/sparta/engineering72/sakilaproject/controller/ActorController.java",
      "category": "controller",
      "className": "ActorController",
      "description": "Controller class converted from Java.",
      "methods": [
        {
          "name": "getActors",
          "signature": "public String getActors(ModelMap modelMap,\n                            @RequestParam(value = \"firstName\", defaultValue = \"ALL ACTORS\")",
          "parameters": [
            "ModelMap modelMap",
            "@RequestParam(value = \"firstName\"",
            "defaultValue = \"ALL ACTORS\""
          ],
          "returnType": "String",
          "description": "Auto-generated description"
        },
        {
          "name": "getActorFilmDetails",
          "signature": "public String getActorFilmDetails(ModelMap modelMap,\n                                      @RequestParam(value = \"id\")",
          "parameters": [
            "ModelMap modelMap",
            "@RequestParam(value = \"id\""
          ],
          "returnType": "String",
          "description": "Auto-generated description"
        },
        {
          "name": "findActorById",
          "signature": "public Actor findActorById(Integer id)",
          "parameters": [
            "Integer id"
          ],
          "returnType": "Actor",
          "description": "Auto-generated description"
        },
        {
          "name": "getActorFullNameFromID",
          "signature": "public String getActorFullNameFromID(Integer id)",
          "parameters": [
            "Integer id"
          ],
          "returnType": "String",
          "description": "Auto-generated description"
        }
      ],
      "complexityLevel": "low",
      "internalDependencies": [],
      "annotations": []
    },
    {
      "filePath": "/home/runner/workspace/java-codebase/src/main/java/com/sparta/engineering72/sakilaproject/controller/CategoryController.java",
      "category": "controller",
      "className": "CategoryController",
      "description": "Controller class converted from Java.",
      "methods": [
        {
          "name": "getCategories",
          "signature": "public String getCategories(ModelMap modelMap)",
          "parameters": [
            "ModelMap modelMap"
          ],
          "returnType": "String",
          "description": "Auto-generated description"
        },
        {
          "name": "getCategoryDetails",
          "signature": "public String getCategoryDetails(ModelMap modelMap,\n                                 @RequestParam(value = \"id\")",
          "parameters": [
            "ModelMap modelMap",
            "@RequestParam(value = \"id\""
          ],
          "returnType": "String",
          "description": "Auto-generated description"
        },
        {
          "name": "getCategoryById",
          "signature": "public Category getCategoryById(Integer id)",
          "parameters": [
            "Integer id"
          ],
          "returnType": "Category",
          "description": "Auto-generated description"
        }
      ],
      "complexityLevel": "low",
      "internalDependencies": [],
      "annotations": []
    },
    {
      "filePath": "/home/runner/workspace/java-codebase/src/main/java/com/sparta/engineering72/sakilaproject/controller/CustomerController.java",
      "category": "controller",
      "className": "CustomerController",
      "description": "Controller class converted from Java.",
      "methods": [
        {
          "name": "currentUser",
          "signature": "public String currentUser(ModelMap modelMap, HttpServletRequest request)",
          "parameters": [
            "ModelMap modelMap",
            "HttpServletRequest request"
          ],
          "returnType": "String",
          "description": "Auto-generated description"
        },
        {
          "name": "getCustomers",
          "signature": "public String getCustomers(ModelMap modelMap,\n                               @RequestParam(value = \"firstName\", defaultValue = \"ALL CUSTOMERS\")",
          "parameters": [
            "ModelMap modelMap",
            "@RequestParam(value = \"firstName\"",
            "defaultValue = \"ALL CUSTOMERS\""
          ],
          "returnType": "String",
          "description": "Auto-generated description"
        },
        {
          "name": "showUsersRentalHistory",
          "signature": "public String showUsersRentalHistory(ModelMap modelMap,\n                                         @PathVariable(name = \"id\")",
          "parameters": [
            "ModelMap modelMap",
            "@PathVariable(name = \"id\""
          ],
          "returnType": "String",
          "description": "Auto-generated description"
        }
      ],
      "complexityLevel": "low",
      "internalDependencies": [],
      "annotations": []
    },
    {
      "filePath": "/home/runner/workspace/java-codebase/src/main/java/com/sparta/engineering72/sakilaproject/controller/FilmController.java",
      "category": "controller",
      "className": "FilmController",
      "description": "Controller class converted from Java.",
      "methods": [
        {
          "name": "getFilms",
          "signature": "public String getFilms(ModelMap modelMap, @RequestParam(value = \"title\", defaultValue = \"ALL FILMS\")",
          "parameters": [
            "ModelMap modelMap",
            "@RequestParam(value = \"title\"",
            "defaultValue = \"ALL FILMS\""
          ],
          "returnType": "String",
          "description": "Auto-generated description"
        },
        {
          "name": "getFilmDetails",
          "signature": "public String getFilmDetails(ModelMap modelMap, @RequestParam(value = \"id\")",
          "parameters": [
            "ModelMap modelMap",
            "@RequestParam(value = \"id\""
          ],
          "returnType": "String",
          "description": "Auto-generated description"
        },
        {
          "name": "rentFilm",
          "signature": "public String rentFilm(ModelMap modelMap, Principal principal,\n                           @PathVariable(\"filmid\")",
          "parameters": [
            "ModelMap modelMap",
            "Principal principal",
            "@PathVariable(\"filmid\""
          ],
          "returnType": "String",
          "description": "Auto-generated description"
        },
        {
          "name": "getFilmDetails",
          "signature": "public String getFilmDetails(ModelMap modelMap,\n                                 @RequestParam(value = \"title\", defaultValue = \"ALL FILMS\")",
          "parameters": [
            "ModelMap modelMap",
            "@RequestParam(value = \"title\"",
            "defaultValue = \"ALL FILMS\""
          ],
          "returnType": "String",
          "description": "Auto-generated description"
        },
        {
          "name": "showEditProductPage",
          "signature": "public ModelAndView showEditProductPage(@PathVariable(name = \"id\")",
          "parameters": [
            "@PathVariable(name = \"id\""
          ],
          "returnType": "ModelAndView",
          "description": "Auto-generated description"
        },
        {
          "name": "deleteProduct",
          "signature": "public String deleteProduct(@PathVariable(name = \"id\")",
          "parameters": [
            "@PathVariable(name = \"id\""
          ],
          "returnType": "String",
          "description": "Auto-generated description"
        },
        {
          "name": "findFilmByID",
          "signature": "public Film findFilmByID(Integer id)",
          "parameters": [
            "Integer id"
          ],
          "returnType": "Film",
          "description": "Auto-generated description"
        }
      ],
      "complexityLevel": "medium",
      "internalDependencies": [],
      "annotations": []
    },
    {
      "filePath": "/home/runner/workspace/java-codebase/src/main/java/com/sparta/engineering72/sakilaproject/controller/MainController.java",
      "category": "controller",
      "className": "MainController",
      "description": "Controller class converted from Java.",
      "methods": [
        {
          "name": "home",
          "signature": "public String home()",
          "parameters": [],
          "returnType": "String",
          "description": "Auto-generated description"
        },
        {
          "name": "login",
          "signature": "public String login()",
          "parameters": [],
          "returnType": "String",
          "description": "Auto-generated description"
        },
        {
          "name": "account",
          "signature": "public String account()",
          "parameters": [],
          "returnType": "String",
          "description": "Auto-generated description"
        }
      ],
      "complexityLevel": "low",
      "internalDependencies": [],
      "annotations": []
    },
    {
      "filePath": "/home/runner/workspace/java-codebase/src/main/java/com/sparta/engineering72/sakilaproject/controller/StaffController.java",
      "category": "controller",
      "className": "StaffController",
      "description": "Controller class converted from Java.",
      "methods": [
        {
          "name": "currentUser",
          "signature": "public String currentUser(ModelMap modelMap, HttpServletRequest request)",
          "parameters": [
            "ModelMap modelMap",
            "HttpServletRequest request"
          ],
          "returnType": "String",
          "description": "Auto-generated description"
        }
      ],
      "complexityLevel": "low",
      "internalDependencies": [],
      "annotations": []
    },
    {
      "filePath": "/home/runner/workspace/java-codebase/src/main/java/com/sparta/engineering72/sakilaproject/entities/Actor.java",
      "category": "other",
      "className": "Actor",
      "description": "Other Java class",
      "methods": [
        {
          "name": "getActorId",
          "signature": "public int getActorId()",
          "parameters": [],
          "returnType": "int",
          "description": "Auto-generated description"
        },
        {
          "name": "setActorId",
          "signature": "public void setActorId(int actorId)",
          "parameters": [
            "int actorId"
          ],
          "returnType": "void",
          "description": "Auto-generated description"
        },
        {
          "name": "getFirstName",
          "signature": "public String getFirstName()",
          "parameters": [],
          "returnType": "String",
          "description": "Auto-generated description"
        },
        {
          "name": "setFirstName",
          "signature": "public void setFirstName(String firstName)",
          "parameters": [
            "String firstName"
          ],
          "returnType": "void",
          "description": "Auto-generated description"
        },
        {
          "name": "getLastName",
          "signature": "public String getLastName()",
          "parameters": [],
          "returnType": "String",
          "description": "Auto-generated description"
        },
        {
          "name": "setLastName",
          "signature": "public void setLastName(String lastName)",
          "parameters": [
            "String lastName"
          ],
          "returnType": "void",
          "description": "Auto-generated description"
        },
        {
          "name": "getLastUpdate",
          "signature": "public Timestamp getLastUpdate()",
          "parameters": [],
          "returnType": "Timestamp",
          "description": "Auto-generated description"
        },
        {
          "name": "setLastUpdate",
          "signature": "public void setLastUpdate(Timestamp lastUpdate)",
          "parameters": [
            "Timestamp lastUpdate"
          ],
          "returnType": "void",
          "description": "Auto-generated description"
        },
        {
          "name": "equals",
          "signature": "public boolean equals(Object o)",
          "parameters": [
            "Object o"
          ],
          "returnType": "boolean",
          "description": "Auto-generated description"
        },
        {
          "name": "hashCode",
          "signature": "public int hashCode()",
          "parameters": [],
          "returnType": "int",
          "description": "Auto-generated description"
        }
      ],
      "complexityLevel": "medium",
      "internalDependencies": [],
      "annotations": []
    },
    {
      "filePath": "/home/runner/workspace/java-codebase/src/main/java/com/sparta/engineering72/sakilaproject/entities/Category.java",
      "category": "other",
      "className": "Category",
      "description": "Other Java class",
      "methods": [
        {
          "name": "getCategoryId",
          "signature": "public int getCategoryId()",
          "parameters": [],
          "returnType": "int",
          "description": "Auto-generated description"
        },
        {
          "name": "setCategoryId",
          "signature": "public void setCategoryId(int categoryId)",
          "parameters": [
            "int categoryId"
          ],
          "returnType": "void",
          "description": "Auto-generated description"
        },
        {
          "name": "getName",
          "signature": "public String getName()",
          "parameters": [],
          "returnType": "String",
          "description": "Auto-generated description"
        },
        {
          "name": "setName",
          "signature": "public void setName(String name)",
          "parameters": [
            "String name"
          ],
          "returnType": "void",
          "description": "Auto-generated description"
        },
        {
          "name": "getLastUpdate",
          "signature": "public Timestamp getLastUpdate()",
          "parameters": [],
          "returnType": "Timestamp",
          "description": "Auto-generated description"
        },
        {
          "name": "setLastUpdate",
          "signature": "public void setLastUpdate(Timestamp lastUpdate)",
          "parameters": [
            "Timestamp lastUpdate"
          ],
          "returnType": "void",
          "description": "Auto-generated description"
        },
        {
          "name": "equals",
          "signature": "public boolean equals(Object o)",
          "parameters": [
            "Object o"
          ],
          "returnType": "boolean",
          "description": "Auto-generated description"
        },
        {
          "name": "hashCode",
          "signature": "public int hashCode()",
          "parameters": [],
          "returnType": "int",
          "description": "Auto-generated description"
        }
      ],
      "complexityLevel": "medium",
      "internalDependencies": [],
      "annotations": []
    },
    {
      "filePath": "/home/runner/workspace/java-codebase/src/main/java/com/sparta/engineering72/sakilaproject/entities/Customer.java",
      "category": "other",
      "className": "Customer",
      "description": "Other Java class",
      "methods": [
        {
          "name": "getCustomerId",
          "signature": "public int getCustomerId()",
          "parameters": [],
          "returnType": "int",
          "description": "Auto-generated description"
        },
        {
          "name": "setCustomerId",
          "signature": "public void setCustomerId(int customerId)",
          "parameters": [
            "int customerId"
          ],
          "returnType": "void",
          "description": "Auto-generated description"
        },
        {
          "name": "getFirstName",
          "signature": "public String getFirstName()",
          "parameters": [],
          "returnType": "String",
          "description": "Auto-generated description"
        },
        {
          "name": "setFirstName",
          "signature": "public void setFirstName(String firstName)",
          "parameters": [
            "String firstName"
          ],
          "returnType": "void",
          "description": "Auto-generated description"
        },
        {
          "name": "getLastName",
          "signature": "public String getLastName()",
          "parameters": [],
          "returnType": "String",
          "description": "Auto-generated description"
        },
        {
          "name": "setLastName",
          "signature": "public void setLastName(String lastName)",
          "parameters": [
            "String lastName"
          ],
          "returnType": "void",
          "description": "Auto-generated description"
        },
        {
          "name": "getEmail",
          "signature": "public String getEmail()",
          "parameters": [],
          "returnType": "String",
          "description": "Auto-generated description"
        },
        {
          "name": "setEmail",
          "signature": "public void setEmail(String email)",
          "parameters": [
            "String email"
          ],
          "returnType": "void",
          "description": "Auto-generated description"
        },
        {
          "name": "getActive",
          "signature": "public byte getActive()",
          "parameters": [],
          "returnType": "byte",
          "description": "Auto-generated description"
        },
        {
          "name": "setActive",
          "signature": "public void setActive(byte active)",
          "parameters": [
            "byte active"
          ],
          "returnType": "void",
          "description": "Auto-generated description"
        },
        {
          "name": "getCreateDate",
          "signature": "public Timestamp getCreateDate()",
          "parameters": [],
          "returnType": "Timestamp",
          "description": "Auto-generated description"
        },
        {
          "name": "setCreateDate",
          "signature": "public void setCreateDate(Timestamp createDate)",
          "parameters": [
            "Timestamp createDate"
          ],
          "returnType": "void",
          "description": "Auto-generated description"
        },
        {
          "name": "getLastUpdate",
          "signature": "public Timestamp getLastUpdate()",
          "parameters": [],
          "returnType": "Timestamp",
          "description": "Auto-generated description"
        },
        {
          "name": "setLastUpdate",
          "signature": "public void setLastUpdate(Timestamp lastUpdate)",
          "parameters": [
            "Timestamp lastUpdate"
          ],
          "returnType": "void",
          "description": "Auto-generated description"
        },
        {
          "name": "equals",
          "signature": "public boolean equals(Object o)",
          "parameters": [
            "Object o"
          ],
          "returnType": "boolean",
          "description": "Auto-generated description"
        },
        {
          "name": "hashCode",
          "signature": "public int hashCode()",
          "parameters": [],
          "returnType": "int",
          "description": "Auto-generated description"
        }
      ],
      "complexityLevel": "medium",
      "internalDependencies": [],
      "annotations": []
    },
    {
      "filePath": "/home/runner/workspace/java-codebase/src/main/java/com/sparta/engineering72/sakilaproject/entities/Film.java",
      "category": "other",
      "className": "Film",
      "description": "Other Java class",
      "methods": [
        {
          "name": "getFilmId",
          "signature": "public int getFilmId()",
          "parameters": [],
          "returnType": "int",
          "description": "Auto-generated description"
        },
        {
          "name": "setFilmId",
          "signature": "public void setFilmId(int filmId)",
          "parameters": [
            "int filmId"
          ],
          "returnType": "void",
          "description": "Auto-generated description"
        },
        {
          "name": "getTitle",
          "signature": "public String getTitle()",
          "parameters": [],
          "returnType": "String",
          "description": "Auto-generated description"
        },
        {
          "name": "setTitle",
          "signature": "public void setTitle(String title)",
          "parameters": [
            "String title"
          ],
          "returnType": "void",
          "description": "Auto-generated description"
        },
        {
          "name": "getDescription",
          "signature": "public String getDescription()",
          "parameters": [],
          "returnType": "String",
          "description": "Auto-generated description"
        },
        {
          "name": "setDescription",
          "signature": "public void setDescription(String description)",
          "parameters": [
            "String description"
          ],
          "returnType": "void",
          "description": "Auto-generated description"
        },
        {
          "name": "getReleaseYear",
          "signature": "public int getReleaseYear()",
          "parameters": [],
          "returnType": "int",
          "description": "Auto-generated description"
        },
        {
          "name": "setReleaseYear",
          "signature": "public void setReleaseYear(int releaseYear)",
          "parameters": [
            "int releaseYear"
          ],
          "returnType": "void",
          "description": "Auto-generated description"
        },
        {
          "name": "getRentalDuration",
          "signature": "public Integer getRentalDuration()",
          "parameters": [],
          "returnType": "Integer",
          "description": "Auto-generated description"
        },
        {
          "name": "setRentalDuration",
          "signature": "public void setRentalDuration(Integer rentalDuration)",
          "parameters": [
            "Integer rentalDuration"
          ],
          "returnType": "void",
          "description": "Auto-generated description"
        },
        {
          "name": "getRentalRate",
          "signature": "public BigDecimal getRentalRate()",
          "parameters": [],
          "returnType": "BigDecimal",
          "description": "Auto-generated description"
        },
        {
          "name": "setRentalRate",
          "signature": "public void setRentalRate(BigDecimal rentalRate)",
          "parameters": [
            "BigDecimal rentalRate"
          ],
          "returnType": "void",
          "description": "Auto-generated description"
        },
        {
          "name": "getLength",
          "signature": "public Integer getLength()",
          "parameters": [],
          "returnType": "Integer",
          "description": "Auto-generated description"
        },
        {
          "name": "setLength",
          "signature": "public void setLength(Integer length)",
          "parameters": [
            "Integer length"
          ],
          "returnType": "void",
          "description": "Auto-generated description"
        },
        {
          "name": "getReplacementCost",
          "signature": "public BigDecimal getReplacementCost()",
          "parameters": [],
          "returnType": "BigDecimal",
          "description": "Auto-generated description"
        },
        {
          "name": "setReplacementCost",
          "signature": "public void setReplacementCost(BigDecimal replacementCost)",
          "parameters": [
            "BigDecimal replacementCost"
          ],
          "returnType": "void",
          "description": "Auto-generated description"
        },
        {
          "name": "getRating",
          "signature": "public String getRating()",
          "parameters": [],
          "returnType": "String",
          "description": "Auto-generated description"
        },
        {
          "name": "setRating",
          "signature": "public void setRating(String rating)",
          "parameters": [
            "String rating"
          ],
          "returnType": "void",
          "description": "Auto-generated description"
        },
        {
          "name": "getSpecialFeatures",
          "signature": "public String getSpecialFeatures()",
          "parameters": [],
          "returnType": "String",
          "description": "Auto-generated description"
        },
        {
          "name": "setSpecialFeatures",
          "signature": "public void setSpecialFeatures(String specialFeatures)",
          "parameters": [
            "String specialFeatures"
          ],
          "returnType": "void",
          "description": "Auto-generated description"
        },
        {
          "name": "getLastUpdate",
          "signature": "public Timestamp getLastUpdate()",
          "parameters": [],
          "returnType": "Timestamp",
          "description": "Auto-generated description"
        },
        {
          "name": "setLastUpdate",
          "signature": "public void setLastUpdate(Timestamp lastUpdate)",
          "parameters": [
            "Timestamp lastUpdate"
          ],
          "returnType": "void",
          "description": "Auto-generated description"
        },
        {
          "name": "equals",
          "signature": "public boolean equals(Object o)",
          "parameters": [
            "Object o"
          ],
          "returnType": "boolean",
          "description": "Auto-generated description"
        },
        {
          "name": "hashCode",
          "signature": "public int hashCode()",
          "parameters": [],
          "returnType": "int",
          "description": "Auto-generated description"
        }
      ],
      "complexityLevel": "medium",
      "internalDependencies": [],
      "annotations": []
    },
    {
      "filePath": "/home/runner/workspace/java-codebase/src/main/java/com/sparta/engineering72/sakilaproject/entities/FilmActor.java",
      "category": "other",
      "className": "FilmActor",
      "description": "Other Java class",
      "methods": [
        {
          "name": "getActorId",
          "signature": "public int getActorId()",
          "parameters": [],
          "returnType": "int",
          "description": "Auto-generated description"
        },
        {
          "name": "setActorId",
          "signature": "public void setActorId(int actorId)",
          "parameters": [
            "int actorId"
          ],
          "returnType": "void",
          "description": "Auto-generated description"
        },
        {
          "name": "getFilmId",
          "signature": "public int getFilmId()",
          "parameters": [],
          "returnType": "int",
          "description": "Auto-generated description"
        },
        {
          "name": "setFilmId",
          "signature": "public void setFilmId(int filmId)",
          "parameters": [
            "int filmId"
          ],
          "returnType": "void",
          "description": "Auto-generated description"
        },
        {
          "name": "getLastUpdate",
          "signature": "public Timestamp getLastUpdate()",
          "parameters": [],
          "returnType": "Timestamp",
          "description": "Auto-generated description"
        },
        {
          "name": "setLastUpdate",
          "signature": "public void setLastUpdate(Timestamp lastUpdate)",
          "parameters": [
            "Timestamp lastUpdate"
          ],
          "returnType": "void",
          "description": "Auto-generated description"
        },
        {
          "name": "equals",
          "signature": "public boolean equals(Object o)",
          "parameters": [
            "Object o"
          ],
          "returnType": "boolean",
          "description": "Auto-generated description"
        },
        {
          "name": "hashCode",
          "signature": "public int hashCode()",
          "parameters": [],
          "returnType": "int",
          "description": "Auto-generated description"
        }
      ],
      "complexityLevel": "medium",
      "internalDependencies": [],
      "annotations": []
    },
    {
      "filePath": "/home/runner/workspace/java-codebase/src/main/java/com/sparta/engineering72/sakilaproject/entities/FilmActorPK.java",
      "category": "other",
      "className": "FilmActorPK",
      "description": "Other Java class",
      "methods": [
        {
          "name": "getActorId",
          "signature": "public Integer getActorId()",
          "parameters": [],
          "returnType": "Integer",
          "description": "Auto-generated description"
        },
        {
          "name": "setActorId",
          "signature": "public void setActorId(int actorId)",
          "parameters": [
            "int actorId"
          ],
          "returnType": "void",
          "description": "Auto-generated description"
        },
        {
          "name": "getFilmId",
          "signature": "public int getFilmId()",
          "parameters": [],
          "returnType": "int",
          "description": "Auto-generated description"
        },
        {
          "name": "setFilmId",
          "signature": "public void setFilmId(int filmId)",
          "parameters": [
            "int filmId"
          ],
          "returnType": "void",
          "description": "Auto-generated description"
        },
        {
          "name": "equals",
          "signature": "public boolean equals(Object o)",
          "parameters": [
            "Object o"
          ],
          "returnType": "boolean",
          "description": "Auto-generated description"
        },
        {
          "name": "hashCode",
          "signature": "public int hashCode()",
          "parameters": [],
          "returnType": "int",
          "description": "Auto-generated description"
        }
      ],
      "complexityLevel": "medium",
      "internalDependencies": [],
      "annotations": []
    },
    {
      "filePath": "/home/runner/workspace/java-codebase/src/main/java/com/sparta/engineering72/sakilaproject/entities/FilmCategory.java",
      "category": "other",
      "className": "FilmCategory",
      "description": "Other Java class",
      "methods": [
        {
          "name": "getFilmId",
          "signature": "public int getFilmId()",
          "parameters": [],
          "returnType": "int",
          "description": "Auto-generated description"
        },
        {
          "name": "setFilmId",
          "signature": "public void setFilmId(Integer filmId)",
          "parameters": [
            "Integer filmId"
          ],
          "returnType": "void",
          "description": "Auto-generated description"
        },
        {
          "name": "getCategoryId",
          "signature": "public int getCategoryId()",
          "parameters": [],
          "returnType": "int",
          "description": "Auto-generated description"
        },
        {
          "name": "setCategoryId",
          "signature": "public void setCategoryId(Integer categoryId)",
          "parameters": [
            "Integer categoryId"
          ],
          "returnType": "void",
          "description": "Auto-generated description"
        },
        {
          "name": "getLastUpdate",
          "signature": "public Timestamp getLastUpdate()",
          "parameters": [],
          "returnType": "Timestamp",
          "description": "Auto-generated description"
        },
        {
          "name": "setLastUpdate",
          "signature": "public void setLastUpdate(Timestamp lastUpdate)",
          "parameters": [
            "Timestamp lastUpdate"
          ],
          "returnType": "void",
          "description": "Auto-generated description"
        },
        {
          "name": "equals",
          "signature": "public boolean equals(Object o)",
          "parameters": [
            "Object o"
          ],
          "returnType": "boolean",
          "description": "Auto-generated description"
        },
        {
          "name": "hashCode",
          "signature": "public int hashCode()",
          "parameters": [],
          "returnType": "int",
          "description": "Auto-generated description"
        }
      ],
      "complexityLevel": "medium",
      "internalDependencies": [],
      "annotations": []
    },
    {
      "filePath": "/home/runner/workspace/java-codebase/src/main/java/com/sparta/engineering72/sakilaproject/entities/FilmCategoryPK.java",
      "category": "other",
      "className": "FilmCategoryPK",
      "description": "Other Java class",
      "methods": [
        {
          "name": "getFilmId",
          "signature": "public int getFilmId()",
          "parameters": [],
          "returnType": "int",
          "description": "Auto-generated description"
        },
        {
          "name": "setFilmId",
          "signature": "public void setFilmId(int filmId)",
          "parameters": [
            "int filmId"
          ],
          "returnType": "void",
          "description": "Auto-generated description"
        },
        {
          "name": "getCategoryId",
          "signature": "public int getCategoryId()",
          "parameters": [],
          "returnType": "int",
          "description": "Auto-generated description"
        },
        {
          "name": "setCategoryId",
          "signature": "public void setCategoryId(int categoryId)",
          "parameters": [
            "int categoryId"
          ],
          "returnType": "void",
          "description": "Auto-generated description"
        },
        {
          "name": "equals",
          "signature": "public boolean equals(Object o)",
          "parameters": [
            "Object o"
          ],
          "returnType": "boolean",
          "description": "Auto-generated description"
        },
        {
          "name": "hashCode",
          "signature": "public int hashCode()",
          "parameters": [],
          "returnType": "int",
          "description": "Auto-generated description"
        }
      ],
      "complexityLevel": "medium",
      "internalDependencies": [],
      "annotations": []
    },
    {
      "filePath": "/home/runner/workspace/java-codebase/src/main/java/com/sparta/engineering72/sakilaproject/entities/FilmText.java",
      "category": "other",
      "className": "FilmText",
      "description": "Other Java class",
      "methods": [
        {
          "name": "getFilmId",
          "signature": "public int getFilmId()",
          "parameters": [],
          "returnType": "int",
          "description": "Auto-generated description"
        },
        {
          "name": "setFilmId",
          "signature": "public void setFilmId(int filmId)",
          "parameters": [
            "int filmId"
          ],
          "returnType": "void",
          "description": "Auto-generated description"
        },
        {
          "name": "getTitle",
          "signature": "public String getTitle()",
          "parameters": [],
          "returnType": "String",
          "description": "Auto-generated description"
        },
        {
          "name": "setTitle",
          "signature": "public void setTitle(String title)",
          "parameters": [
            "String title"
          ],
          "returnType": "void",
          "description": "Auto-generated description"
        },
        {
          "name": "getDescription",
          "signature": "public String getDescription()",
          "parameters": [],
          "returnType": "String",
          "description": "Auto-generated description"
        },
        {
          "name": "setDescription",
          "signature": "public void setDescription(String description)",
          "parameters": [
            "String description"
          ],
          "returnType": "void",
          "description": "Auto-generated description"
        },
        {
          "name": "equals",
          "signature": "public boolean equals(Object o)",
          "parameters": [
            "Object o"
          ],
          "returnType": "boolean",
          "description": "Auto-generated description"
        },
        {
          "name": "hashCode",
          "signature": "public int hashCode()",
          "parameters": [],
          "returnType": "int",
          "description": "Auto-generated description"
        }
      ],
      "complexityLevel": "medium",
      "internalDependencies": [],
      "annotations": []
    },
    {
      "filePath": "/home/runner/workspace/java-codebase/src/main/java/com/sparta/engineering72/sakilaproject/entities/Inventory.java",
      "category": "other",
      "className": "Inventory",
      "description": "Other Java class",
      "methods": [
        {
          "name": "getInventoryId",
          "signature": "public int getInventoryId()",
          "parameters": [],
          "returnType": "int",
          "description": "Auto-generated description"
        },
        {
          "name": "setInventoryId",
          "signature": "public void setInventoryId(int inventoryId)",
          "parameters": [
            "int inventoryId"
          ],
          "returnType": "void",
          "description": "Auto-generated description"
        },
        {
          "name": "getFilmId",
          "signature": "public int getFilmId()",
          "parameters": [],
          "returnType": "int",
          "description": "Auto-generated description"
        },
        {
          "name": "setFilmId",
          "signature": "public void setFilmId(int filmId)",
          "parameters": [
            "int filmId"
          ],
          "returnType": "void",
          "description": "Auto-generated description"
        },
        {
          "name": "getLastUpdate",
          "signature": "public Timestamp getLastUpdate()",
          "parameters": [],
          "returnType": "Timestamp",
          "description": "Auto-generated description"
        },
        {
          "name": "setLastUpdate",
          "signature": "public void setLastUpdate(Timestamp lastUpdate)",
          "parameters": [
            "Timestamp lastUpdate"
          ],
          "returnType": "void",
          "description": "Auto-generated description"
        },
        {
          "name": "equals",
          "signature": "public boolean equals(Object o)",
          "parameters": [
            "Object o"
          ],
          "returnType": "boolean",
          "description": "Auto-generated description"
        },
        {
          "name": "hashCode",
          "signature": "public int hashCode()",
          "parameters": [],
          "returnType": "int",
          "description": "Auto-generated description"
        }
      ],
      "complexityLevel": "medium",
      "internalDependencies": [],
      "annotations": []
    },
    {
      "filePath": "/home/runner/workspace/java-codebase/src/main/java/com/sparta/engineering72/sakilaproject/entities/Order.java",
      "category": "other",
      "className": "Order",
      "description": "Other Java class",
      "methods": [
        {
          "name": "getCustomer",
          "signature": "public Customer getCustomer()",
          "parameters": [],
          "returnType": "Customer",
          "description": "Auto-generated description"
        },
        {
          "name": "setCustomer",
          "signature": "public void setCustomer(Customer customer)",
          "parameters": [
            "Customer customer"
          ],
          "returnType": "void",
          "description": "Auto-generated description"
        },
        {
          "name": "getFilm",
          "signature": "public Film getFilm()",
          "parameters": [],
          "returnType": "Film",
          "description": "Auto-generated description"
        },
        {
          "name": "setFilm",
          "signature": "public void setFilm(Film film)",
          "parameters": [
            "Film film"
          ],
          "returnType": "void",
          "description": "Auto-generated description"
        },
        {
          "name": "getRental",
          "signature": "public Rental getRental()",
          "parameters": [],
          "returnType": "Rental",
          "description": "Auto-generated description"
        },
        {
          "name": "setRental",
          "signature": "public void setRental(Rental rental)",
          "parameters": [
            "Rental rental"
          ],
          "returnType": "void",
          "description": "Auto-generated description"
        }
      ],
      "complexityLevel": "medium",
      "internalDependencies": [],
      "annotations": []
    },
    {
      "filePath": "/home/runner/workspace/java-codebase/src/main/java/com/sparta/engineering72/sakilaproject/entities/Rental.java",
      "category": "other",
      "className": "Rental",
      "description": "Other Java class",
      "methods": [
        {
          "name": "getRentalId",
          "signature": "public int getRentalId()",
          "parameters": [],
          "returnType": "int",
          "description": "Auto-generated description"
        },
        {
          "name": "setRentalId",
          "signature": "public void setRentalId(int rentalId)",
          "parameters": [
            "int rentalId"
          ],
          "returnType": "void",
          "description": "Auto-generated description"
        },
        {
          "name": "getRentalDate",
          "signature": "public Timestamp getRentalDate()",
          "parameters": [],
          "returnType": "Timestamp",
          "description": "Auto-generated description"
        },
        {
          "name": "setRentalDate",
          "signature": "public void setRentalDate(Timestamp rentalDate)",
          "parameters": [
            "Timestamp rentalDate"
          ],
          "returnType": "void",
          "description": "Auto-generated description"
        },
        {
          "name": "getInventoryId",
          "signature": "public int getInventoryId()",
          "parameters": [],
          "returnType": "int",
          "description": "Auto-generated description"
        },
        {
          "name": "setInventoryId",
          "signature": "public void setInventoryId(int inventoryId)",
          "parameters": [
            "int inventoryId"
          ],
          "returnType": "void",
          "description": "Auto-generated description"
        },
        {
          "name": "getCustomerId",
          "signature": "public int getCustomerId()",
          "parameters": [],
          "returnType": "int",
          "description": "Auto-generated description"
        },
        {
          "name": "setCustomerId",
          "signature": "public void setCustomerId(int customerId)",
          "parameters": [
            "int customerId"
          ],
          "returnType": "void",
          "description": "Auto-generated description"
        },
        {
          "name": "getReturnDate",
          "signature": "public Timestamp getReturnDate()",
          "parameters": [],
          "returnType": "Timestamp",
          "description": "Auto-generated description"
        },
        {
          "name": "setReturnDate",
          "signature": "public void setReturnDate(Timestamp returnDate)",
          "parameters": [
            "Timestamp returnDate"
          ],
          "returnType": "void",
          "description": "Auto-generated description"
        },
        {
          "name": "getStaffId",
          "signature": "public int getStaffId()",
          "parameters": [],
          "returnType": "int",
          "description": "Auto-generated description"
        },
        {
          "name": "setStaffId",
          "signature": "public void setStaffId(int staffId)",
          "parameters": [
            "int staffId"
          ],
          "returnType": "void",
          "description": "Auto-generated description"
        },
        {
          "name": "getLastUpdate",
          "signature": "public Timestamp getLastUpdate()",
          "parameters": [],
          "returnType": "Timestamp",
          "description": "Auto-generated description"
        },
        {
          "name": "setLastUpdate",
          "signature": "public void setLastUpdate(Timestamp lastUpdate)",
          "parameters": [
            "Timestamp lastUpdate"
          ],
          "returnType": "void",
          "description": "Auto-generated description"
        },
        {
          "name": "equals",
          "signature": "public boolean equals(Object o)",
          "parameters": [
            "Object o"
          ],
          "returnType": "boolean",
          "description": "Auto-generated description"
        },
        {
          "name": "hashCode",
          "signature": "public int hashCode()",
          "parameters": [],
          "returnType": "int",
          "description": "Auto-generated description"
        }
      ],
      "complexityLevel": "medium",
      "internalDependencies": [],
      "annotations": []
    },
    {
      "filePath": "/home/runner/workspace/java-codebase/src/main/java/com/sparta/engineering72/sakilaproject/entities/Staff.java",
      "category": "other",
      "className": "Staff",
      "description": "Other Java class",
      "methods": [
        {
          "name": "getStaffId",
          "signature": "public int getStaffId()",
          "parameters": [],
          "returnType": "int",
          "description": "Auto-generated description"
        },
        {
          "name": "setStaffId",
          "signature": "public void setStaffId(int staffId)",
          "parameters": [
            "int staffId"
          ],
          "returnType": "void",
          "description": "Auto-generated description"
        },
        {
          "name": "getFirstName",
          "signature": "public String getFirstName()",
          "parameters": [],
          "returnType": "String",
          "description": "Auto-generated description"
        },
        {
          "name": "setFirstName",
          "signature": "public void setFirstName(String firstName)",
          "parameters": [
            "String firstName"
          ],
          "returnType": "void",
          "description": "Auto-generated description"
        },
        {
          "name": "getLastName",
          "signature": "public String getLastName()",
          "parameters": [],
          "returnType": "String",
          "description": "Auto-generated description"
        },
        {
          "name": "setLastName",
          "signature": "public void setLastName(String lastName)",
          "parameters": [
            "String lastName"
          ],
          "returnType": "void",
          "description": "Auto-generated description"
        },
        {
          "name": "getPicture",
          "signature": "public byte[] getPicture()",
          "parameters": [],
          "returnType": "byte[]",
          "description": "Auto-generated description"
        },
        {
          "name": "setPicture",
          "signature": "public void setPicture(byte[] picture)",
          "parameters": [
            "byte[] picture"
          ],
          "returnType": "void",
          "description": "Auto-generated description"
        },
        {
          "name": "getEmail",
          "signature": "public String getEmail()",
          "parameters": [],
          "returnType": "String",
          "description": "Auto-generated description"
        },
        {
          "name": "setEmail",
          "signature": "public void setEmail(String email)",
          "parameters": [
            "String email"
          ],
          "returnType": "void",
          "description": "Auto-generated description"
        },
        {
          "name": "getActive",
          "signature": "public byte getActive()",
          "parameters": [],
          "returnType": "byte",
          "description": "Auto-generated description"
        },
        {
          "name": "setActive",
          "signature": "public void setActive(byte active)",
          "parameters": [
            "byte active"
          ],
          "returnType": "void",
          "description": "Auto-generated description"
        },
        {
          "name": "getUsername",
          "signature": "public String getUsername()",
          "parameters": [],
          "returnType": "String",
          "description": "Auto-generated description"
        },
        {
          "name": "setUsername",
          "signature": "public void setUsername(String username)",
          "parameters": [
            "String username"
          ],
          "returnType": "void",
          "description": "Auto-generated description"
        },
        {
          "name": "getPassword",
          "signature": "public String getPassword()",
          "parameters": [],
          "returnType": "String",
          "description": "Auto-generated description"
        },
        {
          "name": "setPassword",
          "signature": "public void setPassword(String password)",
          "parameters": [
            "String password"
          ],
          "returnType": "void",
          "description": "Auto-generated description"
        },
        {
          "name": "getLastUpdate",
          "signature": "public Timestamp getLastUpdate()",
          "parameters": [],
          "returnType": "Timestamp",
          "description": "Auto-generated description"
        },
        {
          "name": "setLastUpdate",
          "signature": "public void setLastUpdate(Timestamp lastUpdate)",
          "parameters": [
            "Timestamp lastUpdate"
          ],
          "returnType": "void",
          "description": "Auto-generated description"
        },
        {
          "name": "equals",
          "signature": "public boolean equals(Object o)",
          "parameters": [
            "Object o"
          ],
          "returnType": "boolean",
          "description": "Auto-generated description"
        },
        {
          "name": "hashCode",
          "signature": "public int hashCode()",
          "parameters": [],
          "returnType": "int",
          "description": "Auto-generated description"
        }
      ],
      "complexityLevel": "medium",
      "internalDependencies": [],
      "annotations": []
    },
    {
      "filePath": "/home/runner/workspace/java-codebase/src/main/java/com/sparta/engineering72/sakilaproject/respositories/ActorRepository.java",
      "category": "dao",
      "className": "ActorRepository",
      "description": "DAO/Repository class converted from Java.",
      "methods": [],
      "complexityLevel": "low",
      "internalDependencies": [],
      "annotations": []
    },
    {
      "filePath": "/home/runner/workspace/java-codebase/src/main/java/com/sparta/engineering72/sakilaproject/respositories/CategoryRepository.java",
      "category": "dao",
      "className": "CategoryRepository",
      "description": "DAO/Repository class converted from Java.",
      "methods": [],
      "complexityLevel": "low",
      "internalDependencies": [],
      "annotations": []
    },
    {
      "filePath": "/home/runner/workspace/java-codebase/src/main/java/com/sparta/engineering72/sakilaproject/respositories/CustomerRepository.java",
      "category": "dao",
      "className": "CustomerRepository",
      "description": "DAO/Repository class converted from Java.",
      "methods": [],
      "complexityLevel": "low",
      "internalDependencies": [],
      "annotations": []
    },
    {
      "filePath": "/home/runner/workspace/java-codebase/src/main/java/com/sparta/engineering72/sakilaproject/respositories/FilmRepository.java",
      "category": "dao",
      "className": "FilmRepository",
      "description": "DAO/Repository class converted from Java.",
      "methods": [],
      "complexityLevel": "low",
      "internalDependencies": [],
      "annotations": []
    },
    {
      "filePath": "/home/runner/workspace/java-codebase/src/main/java/com/sparta/engineering72/sakilaproject/respositories/InventoryRepository.java",
      "category": "dao",
      "className": "InventoryRepository",
      "description": "DAO/Repository class converted from Java.",
      "methods": [],
      "complexityLevel": "low",
      "internalDependencies": [],
      "annotations": []
    },
    {
      "filePath": "/home/runner/workspace/java-codebase/src/main/java/com/sparta/engineering72/sakilaproject/respositories/RentalRepository.java",
      "category": "dao",
      "className": "RentalRepository",
      "description": "DAO/Repository class converted from Java.",
      "methods": [],
      "complexityLevel": "low",
      "internalDependencies": [],
      "annotations": []
    },
    {
      "filePath": "/home/runner/workspace/java-codebase/src/main/java/com/sparta/engineering72/sakilaproject/respositories/StaffRepository.java",
      "category": "dao",
      "className": "StaffRepository",
      "description": "DAO/Repository class converted from Java.",
      "methods": [],
      "complexityLevel": "low",
      "internalDependencies": [],
      "annotations": []
    },
    {
      "filePath": "/home/runner/workspace/java-codebase/src/main/java/com/sparta/engineering72/sakilaproject/securingweb/FailureHandler.java",
      "category": "other",
      "className": "FailureHandler",
      "description": "Other Java class",
      "methods": [
        {
          "name": "handle",
          "signature": "public void handle(HttpServletRequest request, HttpServletResponse response, AccessDeniedException e)",
          "parameters": [
            "HttpServletRequest request",
            "HttpServletResponse response",
            "AccessDeniedException e"
          ],
          "returnType": "void",
          "description": "Auto-generated description"
        }
      ],
      "complexityLevel": "low",
      "internalDependencies": [],
      "annotations": []
    },
    {
      "filePath": "/home/runner/workspace/java-codebase/src/main/java/com/sparta/engineering72/sakilaproject/securingweb/MvcConfig.java",
      "category": "other",
      "className": "MvcConfig",
      "description": "Other Java class",
      "methods": [
        {
          "name": "addViewControllers",
          "signature": "public void addViewControllers(ViewControllerRegistry registry)",
          "parameters": [
            "ViewControllerRegistry registry"
          ],
          "returnType": "void",
          "description": "Auto-generated description"
        }
      ],
      "complexityLevel": "low",
      "internalDependencies": [],
      "annotations": []
    },
    {
      "filePath": "/home/runner/workspace/java-codebase/src/main/java/com/sparta/engineering72/sakilaproject/securingweb/SuccessHandler.java",
      "category": "other",
      "className": "SuccessHandler",
      "description": "Other Java class",
      "methods": [
        {
          "name": "onAuthenticationSuccess",
          "signature": "public void onAuthenticationSuccess(HttpServletRequest request, HttpServletResponse response, Authentication authentication)",
          "parameters": [
            "HttpServletRequest request",
            "HttpServletResponse response",
            "Authentication authentication"
          ],
          "returnType": "void",
          "description": "Auto-generated description"
        }
      ],
      "complexityLevel": "low",
      "internalDependencies": [],
      "annotations": []
    },
    {
      "filePath": "/home/runner/workspace/java-codebase/src/main/java/com/sparta/engineering72/sakilaproject/securingweb/UserDetailsServiceImpl.java",
      "category": "other",
      "className": "UserDetailsServiceImpl",
      "description": "Other Java class",
      "methods": [
        {
          "name": "loadUserByUsername",
          "signature": "public UserDetails loadUserByUsername(String anyUsername)",
          "parameters": [
            "String anyUsername"
          ],
          "returnType": "UserDetails",
          "description": "Auto-generated description"
        }
      ],
      "complexityLevel": "low",
      "internalDependencies": [],
      "annotations": []
    },
    {
      "filePath": "/home/runner/workspace/java-codebase/src/main/java/com/sparta/engineering72/sakilaproject/securingweb/WebSecurityConfig.java",
      "category": "other",
      "className": "WebSecurityConfig",
      "description": "Other Java class",
      "methods": [
        {
          "name": "userDetailsService",
          "signature": "public UserDetailsService userDetailsService()",
          "parameters": [],
          "returnType": "UserDetailsService",
          "description": "Auto-generated description"
        },
        {
          "name": "passwordEncoder",
          "signature": "public PasswordEncoder passwordEncoder()",
          "parameters": [],
          "returnType": "PasswordEncoder",
          "description": "Auto-generated description"
        },
        {
          "name": "authenticationProvider",
          "signature": "public DaoAuthenticationProvider authenticationProvider()",
          "parameters": [],
          "returnType": "DaoAuthenticationProvider",
          "description": "Auto-generated description"
        }
      ],
      "complexityLevel": "low",
      "internalDependencies": [],
      "annotations": []
    },
    {
      "filePath": "/home/runner/workspace/java-codebase/src/main/java/com/sparta/engineering72/sakilaproject/services/ActorService.java",
      "category": "other",
      "className": "ActorService",
      "description": "Other Java class",
      "methods": [
        {
          "name": "getAllActors",
          "signature": "public List<Actor> getAllActors()",
          "parameters": [],
          "returnType": "List<Actor>",
          "description": "Auto-generated description"
        },
        {
          "name": "getActorByID",
          "signature": "public Actor getActorByID(int id)",
          "parameters": [
            "int id"
          ],
          "returnType": "Actor",
          "description": "Auto-generated description"
        },
        {
          "name": "getActorsByFullName",
          "signature": "public List<Actor> getActorsByFullName(String firstName, String lastName)",
          "parameters": [
            "String firstName",
            "String lastName"
          ],
          "returnType": "List<Actor>",
          "description": "Auto-generated description"
        },
        {
          "name": "getActorsByFirstName",
          "signature": "public List<Actor> getActorsByFirstName(String firstName)",
          "parameters": [
            "String firstName"
          ],
          "returnType": "List<Actor>",
          "description": "Auto-generated description"
        },
        {
          "name": "getActorsByLastName",
          "signature": "public List<Actor> getActorsByLastName(String lastName)",
          "parameters": [
            "String lastName"
          ],
          "returnType": "List<Actor>",
          "description": "Auto-generated description"
        },
        {
          "name": "getActorFullNameFromID",
          "signature": "public String getActorFullNameFromID(Integer id)",
          "parameters": [
            "Integer id"
          ],
          "returnType": "String",
          "description": "Auto-generated description"
        }
      ],
      "complexityLevel": "medium",
      "internalDependencies": [],
      "annotations": []
    },
    {
      "filePath": "/home/runner/workspace/java-codebase/src/main/java/com/sparta/engineering72/sakilaproject/services/CategoryService.java",
      "category": "other",
      "className": "CategoryService",
      "description": "Other Java class",
      "methods": [
        {
          "name": "getAllCategories",
          "signature": "public List<Category> getAllCategories()",
          "parameters": [],
          "returnType": "List<Category>",
          "description": "Auto-generated description"
        },
        {
          "name": "getByCategoryId",
          "signature": "public Category getByCategoryId(Integer id)",
          "parameters": [
            "Integer id"
          ],
          "returnType": "Category",
          "description": "Auto-generated description"
        }
      ],
      "complexityLevel": "low",
      "internalDependencies": [],
      "annotations": []
    },
    {
      "filePath": "/home/runner/workspace/java-codebase/src/main/java/com/sparta/engineering72/sakilaproject/services/CustomerService.java",
      "category": "other",
      "className": "CustomerService",
      "description": "Other Java class",
      "methods": [
        {
          "name": "getAllCustomers",
          "signature": "public List<Customer> getAllCustomers()",
          "parameters": [],
          "returnType": "List<Customer>",
          "description": "Auto-generated description"
        },
        {
          "name": "getCustomersByFirstName",
          "signature": "public List<Customer> getCustomersByFirstName(String firstName)",
          "parameters": [
            "String firstName"
          ],
          "returnType": "List<Customer>",
          "description": "Auto-generated description"
        },
        {
          "name": "getCustomersByLastName",
          "signature": "public List<Customer> getCustomersByLastName(String lastName)",
          "parameters": [
            "String lastName"
          ],
          "returnType": "List<Customer>",
          "description": "Auto-generated description"
        },
        {
          "name": "getCustomersByFullName",
          "signature": "public List<Customer> getCustomersByFullName(String firstName, String lastName)",
          "parameters": [
            "String firstName",
            "String lastName"
          ],
          "returnType": "List<Customer>",
          "description": "Auto-generated description"
        },
        {
          "name": "getCustomerByID",
          "signature": "public Customer getCustomerByID(int id)",
          "parameters": [
            "int id"
          ],
          "returnType": "Customer",
          "description": "Auto-generated description"
        },
        {
          "name": "getCustomerByEmail",
          "signature": "public Customer getCustomerByEmail(String email)",
          "parameters": [
            "String email"
          ],
          "returnType": "Customer",
          "description": "Auto-generated description"
        },
        {
          "name": "save",
          "signature": "public void save(Customer customer)",
          "parameters": [
            "Customer customer"
          ],
          "returnType": "void",
          "description": "Auto-generated description"
        },
        {
          "name": "getCustomerCount",
          "signature": "public Integer getCustomerCount()",
          "parameters": [],
          "returnType": "Integer",
          "description": "Auto-generated description"
        }
      ],
      "complexityLevel": "medium",
      "internalDependencies": [],
      "annotations": []
    },
    {
      "filePath": "/home/runner/workspace/java-codebase/src/main/java/com/sparta/engineering72/sakilaproject/services/FilmService.java",
      "category": "other",
      "className": "FilmService",
      "description": "Other Java class",
      "methods": [
        {
          "name": "getAllFilms",
          "signature": "public List<Film> getAllFilms()",
          "parameters": [],
          "returnType": "List<Film>",
          "description": "Auto-generated description"
        },
        {
          "name": "getFilmByID",
          "signature": "public Film getFilmByID(int id)",
          "parameters": [
            "int id"
          ],
          "returnType": "Film",
          "description": "Auto-generated description"
        },
        {
          "name": "getFilmsByTitle",
          "signature": "public List<Film> getFilmsByTitle(String title)",
          "parameters": [
            "String title"
          ],
          "returnType": "List<Film>",
          "description": "Auto-generated description"
        },
        {
          "name": "getAvailableFilms",
          "signature": "public List<Film> getAvailableFilms()",
          "parameters": [],
          "returnType": "List<Film>",
          "description": "Auto-generated description"
        },
        {
          "name": "getAvailableFilmCount",
          "signature": "public Integer getAvailableFilmCount(Integer id)",
          "parameters": [
            "Integer id"
          ],
          "returnType": "Integer",
          "description": "Auto-generated description"
        },
        {
          "name": "getFilmsByCategory",
          "signature": "public List<Film> getFilmsByCategory(Integer id)",
          "parameters": [
            "Integer id"
          ],
          "returnType": "List<Film>",
          "description": "Auto-generated description"
        },
        {
          "name": "getFilmsByActor",
          "signature": "public List<Film> getFilmsByActor(Integer id)",
          "parameters": [
            "Integer id"
          ],
          "returnType": "List<Film>",
          "description": "Auto-generated description"
        },
        {
          "name": "save",
          "signature": "public void save(Film film)",
          "parameters": [
            "Film film"
          ],
          "returnType": "void",
          "description": "Auto-generated description"
        },
        {
          "name": "deleteFilmById",
          "signature": "public void deleteFilmById(int id)",
          "parameters": [
            "int id"
          ],
          "returnType": "void",
          "description": "Auto-generated description"
        }
      ],
      "complexityLevel": "medium",
      "internalDependencies": [],
      "annotations": []
    },
    {
      "filePath": "/home/runner/workspace/java-codebase/src/main/java/com/sparta/engineering72/sakilaproject/services/InventoryService.java",
      "category": "other",
      "className": "InventoryService",
      "description": "Other Java class",
      "methods": [
        {
          "name": "getAllInventory",
          "signature": "public List<Inventory> getAllInventory()",
          "parameters": [],
          "returnType": "List<Inventory>",
          "description": "Auto-generated description"
        },
        {
          "name": "getInventoriesById",
          "signature": "public Inventory getInventoriesById(Integer id)",
          "parameters": [
            "Integer id"
          ],
          "returnType": "Inventory",
          "description": "Auto-generated description"
        },
        {
          "name": "deleteInventoryItemById",
          "signature": "public void deleteInventoryItemById(Integer id)",
          "parameters": [
            "Integer id"
          ],
          "returnType": "void",
          "description": "Auto-generated description"
        },
        {
          "name": "getInventoryCount",
          "signature": "public Integer getInventoryCount()",
          "parameters": [],
          "returnType": "Integer",
          "description": "Auto-generated description"
        }
      ],
      "complexityLevel": "low",
      "internalDependencies": [],
      "annotations": []
    },
    {
      "filePath": "/home/runner/workspace/java-codebase/src/main/java/com/sparta/engineering72/sakilaproject/services/RentalService.java",
      "category": "other",
      "className": "RentalService",
      "description": "Other Java class",
      "methods": [
        {
          "name": "getRentalsByCustomer",
          "signature": "public List<Rental> getRentalsByCustomer(Integer id)",
          "parameters": [
            "Integer id"
          ],
          "returnType": "List<Rental>",
          "description": "Auto-generated description"
        },
        {
          "name": "addRental",
          "signature": "public void addRental(int inventoryId, int customerId, Timestamp returnDate)",
          "parameters": [
            "int inventoryId",
            "int customerId",
            "Timestamp returnDate"
          ],
          "returnType": "void",
          "description": "Auto-generated description"
        }
      ],
      "complexityLevel": "low",
      "internalDependencies": [],
      "annotations": []
    },
    {
      "filePath": "/home/runner/workspace/java-codebase/src/main/java/com/sparta/engineering72/sakilaproject/services/StaffService.java",
      "category": "other",
      "className": "StaffService",
      "description": "Other Java class",
      "methods": [
        {
          "name": "getAllStaff",
          "signature": "public List<Staff> getAllStaff()",
          "parameters": [],
          "returnType": "List<Staff>",
          "description": "Auto-generated description"
        },
        {
          "name": "getStaffByUsername",
          "signature": "public Staff getStaffByUsername(String username)",
          "parameters": [
            "String username"
          ],
          "returnType": "Staff",
          "description": "Auto-generated description"
        }
      ],
      "complexityLevel": "low",
      "internalDependencies": [],
      "annotations": []
    }
  ],
  "conversions": [
    {
      "originalFile": "/home/runner/workspace/java-codebase/src/main/java/com/sparta/engineering72/sakilaproject/SakilaProjectApplication.java",
      "convertedFile": "/home/runner/workspace/output/sakilaprojectapplicationother.js",
      "type": "other",
      "className": "SakilaProjectApplication"
    },
    {
      "originalFile": "/home/runner/workspace/java-codebase/src/main/java/com/sparta/engineering72/sakilaproject/controller/ActorController.java",
      "convertedFile": "/home/runner/workspace/output/actorcontrollercontroller.js",
      "type": "controller",
      "className": "ActorController"
    },
    {
      "originalFile": "/home/runner/workspace/java-codebase/src/main/java/com/sparta/engineering72/sakilaproject/controller/CategoryController.java",
      "convertedFile": "/home/runner/workspace/output/categorycontrollercontroller.js",
      "type": "controller",
      "className": "CategoryController"
    },
    {
      "originalFile": "/home/runner/workspace/java-codebase/src/main/java/com/sparta/engineering72/sakilaproject/controller/CustomerController.java",
      "convertedFile": "/home/runner/workspace/output/customercontrollercontroller.js",
      "type": "controller",
      "className": "CustomerController"
    },
    {
      "originalFile": "/home/runner/workspace/java-codebase/src/main/java/com/sparta/engineering72/sakilaproject/controller/FilmController.java",
      "convertedFile": "/home/runner/workspace/output/filmcontrollercontroller.js",
      "type": "controller",
      "className": "FilmController"
    },
    {
      "originalFile": "/home/runner/workspace/java-codebase/src/main/java/com/sparta/engineering72/sakilaproject/controller/MainController.java",
      "convertedFile": "/home/runner/workspace/output/maincontrollercontroller.js",
      "type": "controller",
      "className": "MainController"
    },
    {
      "originalFile": "/home/runner/workspace/java-codebase/src/main/java/com/sparta/engineering72/sakilaproject/controller/StaffController.java",
      "convertedFile": "/home/runner/workspace/output/staffcontrollercontroller.js",
      "type": "controller",
      "className": "StaffController"
    },
    {
      "originalFile": "/home/runner/workspace/java-codebase/src/main/java/com/sparta/engineering72/sakilaproject/entities/Actor.java",
      "convertedFile": "/home/runner/workspace/output/actorother.js",
      "type": "other",
      "className": "Actor"
    },
    {
      "originalFile": "/home/runner/workspace/java-codebase/src/main/java/com/sparta/engineering72/sakilaproject/entities/Category.java",
      "convertedFile": "/home/runner/workspace/output/categoryother.js",
      "type": "other",
      "className": "Category"
    },
    {
      "originalFile": "/home/runner/workspace/java-codebase/src/main/java/com/sparta/engineering72/sakilaproject/entities/Customer.java",
      "convertedFile": "/home/runner/workspace/output/customerother.js",
      "type": "other",
      "className": "Customer"
    },
    {
      "originalFile": "/home/runner/workspace/java-codebase/src/main/java/com/sparta/engineering72/sakilaproject/entities/Film.java",
      "convertedFile": "/home/runner/workspace/output/filmother.js",
      "type": "other",
      "className": "Film"
    },
    {
      "originalFile": "/home/runner/workspace/java-codebase/src/main/java/com/sparta/engineering72/sakilaproject/entities/FilmActor.java",
      "convertedFile": "/home/runner/workspace/output/filmactorother.js",
      "type": "other",
      "className": "FilmActor"
    },
    {
      "originalFile": "/home/runner/workspace/java-codebase/src/main/java/com/sparta/engineering72/sakilaproject/entities/FilmActorPK.java",
      "convertedFile": "/home/runner/workspace/output/filmactorpkother.js",
      "type": "other",
      "className": "FilmActorPK"
    },
    {
      "originalFile": "/home/runner/workspace/java-codebase/src/main/java/com/sparta/engineering72/sakilaproject/entities/FilmCategory.java",
      "convertedFile": "/home/runner/workspace/output/filmcategoryother.js",
      "type": "other",
      "className": "FilmCategory"
    },
    {
      "originalFile": "/home/runner/workspace/java-codebase/src/main/java/com/sparta/engineering72/sakilaproject/entities/FilmCategoryPK.java",
      "convertedFile": "/home/runner/workspace/output/filmcategorypkother.js",
      "type": "other",
      "className": "FilmCategoryPK"
    },
    {
      "originalFile": "/home/runner/workspace/java-codebase/src/main/java/com/sparta/engineering72/sakilaproject/entities/FilmText.java",
      "convertedFile": "/home/runner/workspace/output/filmtextother.js",
      "type": "other",
      "className": "FilmText"
    },
    {
      "originalFile": "/home/runner/workspace/java-codebase/src/main/java/com/sparta/engineering72/sakilaproject/entities/Inventory.java",
      "convertedFile": "/home/runner/workspace/output/inventoryother.js",
      "type": "other",
      "className": "Inventory"
    },
    {
      "originalFile": "/home/runner/workspace/java-codebase/src/main/java/com/sparta/engineering72/sakilaproject/entities/Order.java",
      "convertedFile": "/home/runner/workspace/output/orderother.js",
      "type": "other",
      "className": "Order"
    },
    {
      "originalFile": "/home/runner/workspace/java-codebase/src/main/java/com/sparta/engineering72/sakilaproject/entities/Rental.java",
      "convertedFile": "/home/runner/workspace/output/rentalother.js",
      "type": "other",
      "className": "Rental"
    },
    {
      "originalFile": "/home/runner/workspace/java-codebase/src/main/java/com/sparta/engineering72/sakilaproject/entities/Staff.java",
      "convertedFile": "/home/runner/workspace/output/staffother.js",
      "type": "other",
      "className": "Staff"
    },
    {
      "originalFile": "/home/runner/workspace/java-codebase/src/main/java/com/sparta/engineering72/sakilaproject/respositories/ActorRepository.java",
      "convertedFile": "/home/runner/workspace/output/actorrepositorydao.js",
      "type": "dao",
      "className": "ActorRepository"
    },
    {
      "originalFile": "/home/runner/workspace/java-codebase/src/main/java/com/sparta/engineering72/sakilaproject/respositories/CategoryRepository.java",
      "convertedFile": "/home/runner/workspace/output/categoryrepositorydao.js",
      "type": "dao",
      "className": "CategoryRepository"
    },
    {
      "originalFile": "/home/runner/workspace/java-codebase/src/main/java/com/sparta/engineering72/sakilaproject/respositories/CustomerRepository.java",
      "convertedFile": "/home/runner/workspace/output/customerrepositorydao.js",
      "type": "dao",
      "className": "CustomerRepository"
    },
    {
      "originalFile": "/home/runner/workspace/java-codebase/src/main/java/com/sparta/engineering72/sakilaproject/respositories/FilmRepository.java",
      "convertedFile": "/home/runner/workspace/output/filmrepositorydao.js",
      "type": "dao",
      "className": "FilmRepository"
    },
    {
      "originalFile": "/home/runner/workspace/java-codebase/src/main/java/com/sparta/engineering72/sakilaproject/respositories/InventoryRepository.java",
      "convertedFile": "/home/runner/workspace/output/inventoryrepositorydao.js",
      "type": "dao",
      "className": "InventoryRepository"
    },
    {
      "originalFile": "/home/runner/workspace/java-codebase/src/main/java/com/sparta/engineering72/sakilaproject/respositories/RentalRepository.java",
      "convertedFile": "/home/runner/workspace/output/rentalrepositorydao.js",
      "type": "dao",
      "className": "RentalRepository"
    },
    {
      "originalFile": "/home/runner/workspace/java-codebase/src/main/java/com/sparta/engineering72/sakilaproject/respositories/StaffRepository.java",
      "convertedFile": "/home/runner/workspace/output/staffrepositorydao.js",
      "type": "dao",
      "className": "StaffRepository"
    },
    {
      "originalFile": "/home/runner/workspace/java-codebase/src/main/java/com/sparta/engineering72/sakilaproject/securingweb/FailureHandler.java",
      "convertedFile": "/home/runner/workspace/output/failurehandlerother.js",
      "type": "other",
      "className": "FailureHandler"
    },
    {
      "originalFile": "/home/runner/workspace/java-codebase/src/main/java/com/sparta/engineering72/sakilaproject/securingweb/MvcConfig.java",
      "convertedFile": "/home/runner/workspace/output/mvcconfigother.js",
      "type": "other",
      "className": "MvcConfig"
    },
    {
      "originalFile": "/home/runner/workspace/java-codebase/src/main/java/com/sparta/engineering72/sakilaproject/securingweb/SuccessHandler.java",
      "convertedFile": "/home/runner/workspace/output/successhandlerother.js",
      "type": "other",
      "className": "SuccessHandler"
    },
    {
      "originalFile": "/home/runner/workspace/java-codebase/src/main/java/com/sparta/engineering72/sakilaproject/securingweb/UserDetailsServiceImpl.java",
      "convertedFile": "/home/runner/workspace/output/userdetailsserviceimplother.js",
      "type": "other",
      "className": "UserDetailsServiceImpl"
    },
    {
      "originalFile": "/home/runner/workspace/java-codebase/src/main/java/com/sparta/engineering72/sakilaproject/securingweb/WebSecurityConfig.java",
      "convertedFile": "/home/runner/workspace/output/websecurityconfigother.js",
      "type": "other",
      "className": "WebSecurityConfig"
    },
    {
      "originalFile": "/home/runner/workspace/java-codebase/src/main/java/com/sparta/engineering72/sakilaproject/services/ActorService.java",
      "convertedFile": "/home/runner/workspace/output/actorserviceother.js",
      "type": "other",
      "className": "ActorService"
    },
    {
      "originalFile": "/home/runner/workspace/java-codebase/src/main/java/com/sparta/engineering72/sakilaproject/services/CategoryService.java",
      "convertedFile": "/home/runner/workspace/output/categoryserviceother.js",
      "type": "other",
      "className": "CategoryService"
    },
    {
      "originalFile": "/home/runner/workspace/java-codebase/src/main/java/com/sparta/engineering72/sakilaproject/services/CustomerService.java",
      "convertedFile": "/home/runner/workspace/output/customerserviceother.js",
      "type": "other",
      "className": "CustomerService"
    },
    {
      "originalFile": "/home/runner/workspace/java-codebase/src/main/java/com/sparta/engineering72/sakilaproject/services/FilmService.java",
      "convertedFile": "/home/runner/workspace/output/filmserviceother.js",
      "type": "other",
      "className": "FilmService"
    },
    {
      "originalFile": "/home/runner/workspace/java-codebase/src/main/java/com/sparta/engineering72/sakilaproject/services/InventoryService.java",
      "convertedFile": "/home/runner/workspace/output/inventoryserviceother.js",
      "type": "other",
      "className": "InventoryService"
    },
    {
      "originalFile": "/home/runner/workspace/java-codebase/src/main/java/com/sparta/engineering72/sakilaproject/services/RentalService.java",
      "convertedFile": "/home/runner/workspace/output/rentalserviceother.js",
      "type": "other",
      "className": "RentalService"
    },
    {
      "originalFile": "/home/runner/workspace/java-codebase/src/main/java/com/sparta/engineering72/sakilaproject/services/StaffService.java",
      "convertedFile": "/home/runner/workspace/output/staffserviceother.js",
      "type": "other",
      "className": "StaffService"
    }
  ],
  "summary": {
    "controllers": [
      {
        "className": "ActorController",
        "methods": 4
      },
      {
        "className": "CategoryController",
        "methods": 3
      },
      {
        "className": "CustomerController",
        "methods": 3
      },
      {
        "className": "FilmController",
        "methods": 7
      },
      {
        "className": "MainController",
        "methods": 3
      },
      {
        "className": "StaffController",
        "methods": 1
      }
    ],
    "services": [],
    "daos": [
      {
        "className": "ActorRepository",
        "methods": 0
      },
      {
        "className": "CategoryRepository",
        "methods": 0
      },
      {
        "className": "CustomerRepository",
        "methods": 0
      },
      {
        "className": "FilmRepository",
        "methods": 0
      },
      {
        "className": "InventoryRepository",
        "methods": 0
      },
      {
        "className": "RentalRepository",
        "methods": 0
      },
      {
        "className": "StaffRepository",
        "methods": 0
      }
    ]
  }
}